MANIFEST.in
README.markdown
setup.py
src/django_nudge.egg-info/PKG-INFO
src/django_nudge.egg-info/SOURCES.txt
src/django_nudge.egg-info/dependency_links.txt
src/django_nudge.egg-info/not-zip-safe
src/django_nudge.egg-info/requires.txt
src/django_nudge.egg-info/top_level.txt
src/nudge/__init__.py
src/nudge/admin.py
src/nudge/client.py
src/nudge/exceptions.py
src/nudge/models.py
src/nudge/server.py
src/nudge/tests.py
src/nudge/urls.py
src/nudge/utils.py
src/nudge/views.py
src/nudge/demo/__init__.py
src/nudge/demo/admin.py
src/nudge/demo/models.py
src/nudge/demo/tests.py
src/nudge/demo/views.py
src/nudge/management/__init__.py
src/nudge/management/commands/__init__.py
src/nudge/management/commands/new_nudge_key.py
src/nudge/templates/500.html
src/nudge/templates/admin/nudge/index.html
src/nudge/templates/admin/nudge/batch/_batch_item_row.html
src/nudge/templates/admin/nudge/batch/change_form.html
src/nudge/templates/admin/nudge/batch/push.html
src/nudge/templates/admin/nudge/batch/read_only.html
src/nudge/templates/admin/nudge/batch/submit_line.html
src/nudge/templatetags/__init__.py
src/nudge/templatetags/nudge_admin_helpers.py
src/nudge/templatetags/version_display.py